ArabicOcr/arabicocr.py
ArabicOcr-1.1.6.dist-info/LICENSE
ArabicOcr-1.1.6.dist-info/METADATA
ArabicOcr-1.1.6.dist-info/WHEEL
ArabicOcr-1.1.6.dist-info/top_level.txt
ArabicOcr-1.1.6.dist-info/RECORD
