Metadata-Version: 2.1
Name: ArabicOcr
Version: 1.1.6
Summary: Python package to convert Arabic images to text by OCR technique detection
Home-page: https://iraqprogrammer.wordpress.com/
Author: Falah.G.Saleh
Author-email: falahgs07@gmail.com
License: UNKNOWN
Keywords: arabic ocr,images,dataset images
Platform: UNKNOWN
Classifier: Programming Language :: Python :: 3
Classifier: Programming Language :: Python :: 3.5
Classifier: Programming Language :: Python :: 3.6
Classifier: Programming Language :: Python :: 3.7
Classifier: Programming Language :: Python :: 3.8
Classifier: License :: OSI Approved :: MIT License
Classifier: Operating System :: OS Independent
Requires-Python: >=3.6
Requires-Dist: easyocr
